README.rst
setup.py
Zp/__init__.py
Zp/example.py
Zp/field.py
Zp.egg-info/PKG-INFO
Zp.egg-info/SOURCES.txt
Zp.egg-info/dependency_links.txt
Zp.egg-info/top_level.txt