Metadata-Version: 1.0
Name: Zp
Version: 0.1
Summary: Field Zp module
Home-page:  
Author: Klyuev O. O.
Author-email: tulenivnebe@mail.ru
License: UNKNOWN
Platform: UNKNOWN
